qwlist/__init__.py
qwlist/eager.py
qwlist/qwlist.py
qwlist-2.0.1.dist-info/METADATA
qwlist-2.0.1.dist-info/WHEEL
qwlist-2.0.1.dist-info/RECORD
