Metadata-Version: 2.3
Name: qwlist
Version: 2.0.1
Summary: A small package introducing a new way to use higher order functions with lists
Project-URL: Homepage, https://github.com/WitoldFracek/qlist
Project-URL: Docs, https://witoldfracek.github.io/qlist/
Author: Witold Frącek
Classifier: License :: OSI Approved :: MIT License
Classifier: Operating System :: OS Independent
Classifier: Programming Language :: Python :: 3
Requires-Python: >=3.12
